nwe/__init__.py
nwe/__main__.py
nwe/criaanki.py
nwe/criandopdf.py
nwe/filecsvgoogle.py
nwe/gurafikkuu.py
nwe/jisho.py
nwe/muitoslinks.py
nwe/newswebeasy.py
nwe/usandore.py
nwe-1.0.4.dist-info/LICENSE
nwe-1.0.4.dist-info/METADATA
nwe-1.0.4.dist-info/WHEEL
nwe-1.0.4.dist-info/entry_points.txt
nwe-1.0.4.dist-info/top_level.txt
nwe-1.0.4.dist-info/RECORD
