Metadata-Version: 2.1
Name: nwe
Version: 1.0.4
Summary: Criar Cartões do anki e pdf, do site News Web Easy 
Home-page: https://github.com/narutolavo/nwe
Author: Narutolavo
Author-email: narutoolavo@outlook.com
License: MIT License
Keywords: News Web Easy,Jisho,Anki,Japonês
Platform: UNKNOWN
Classifier: Development Status :: 5 - Production/Stable
Classifier: Intended Audience :: Education
Classifier: Intended Audience :: End Users/Desktop
Classifier: License :: OSI Approved :: MIT License
Classifier: Operating System :: POSIX
Classifier: Operating System :: Microsoft :: Windows
Classifier: Operating System :: MacOS :: MacOS X
Classifier: Topic :: Education
Classifier: Programming Language :: Python
Classifier: Programming Language :: Python :: 3
Classifier: Programming Language :: Python :: 3.6
Classifier: Programming Language :: Python :: 3.7
Classifier: Programming Language :: Python :: 3.8
Requires-Dist: beautifulsoup4
Requires-Dist: googletrans (==4.0.0rc1)
Requires-Dist: reportlab
Requires-Dist: requests
